setup.cfg
setup.py
renderjs_ipyextension/__init__.py
renderjs_ipyextension/renderjs_extension.py
renderjs_ipyextension.egg-info/PKG-INFO
renderjs_ipyextension.egg-info/SOURCES.txt
renderjs_ipyextension.egg-info/dependency_links.txt
renderjs_ipyextension.egg-info/top_level.txt