Metadata-Version: 1.0
Name: renderjs-ipyextension
Version: 0.0.4
Summary: RenderJS gadgets for jupyter (frontend-part)
Home-page: https://lab.nexedi.com/Kreisel/renderjs_extension
Author: Sebastian Kreisel
Author-email: sebastian.kreisel@nexedi.com
License: GPL 2
Keywords: renderjs jupyter nbextension
Platform: UNKNOWN
